locusdb/__init__.py
locusdb/config.py
locusdb/index.py
locusdb/vector.py
locusdb-0.3.0.dist-info/METADATA
locusdb-0.3.0.dist-info/WHEEL
locusdb-0.3.0.dist-info/LICENSE
locusdb-0.3.0.dist-info/RECORD
