Metadata-Version: 2.1
Name: locusdb
Version: 0.3.0
Summary: Local, in-memory vector database
Home-page: https://github.com/the-alex-b/Locus
License: Apache-2.0
Author: Alex
Author-email: 46456279+the-alex-b@users.noreply.github.com
Requires-Python: >=3.9,<4.0
Classifier: License :: OSI Approved :: Apache Software License
Classifier: Programming Language :: Python :: 3
Classifier: Programming Language :: Python :: 3.9
Classifier: Programming Language :: Python :: 3.10
Classifier: Programming Language :: Python :: 3.11
Requires-Dist: hnswlib (>=0.7.0,<0.8.0)
Requires-Dist: numpy (>=1.24.2,<2.0.0)
Project-URL: Repository, https://github.com/the-alex-b/Locus
